GoogleFormSpam/SpamForm.py
GoogleFormSpam/__init__.py
GoogleFormSpam-0.0.1.dist-info/METADATA
GoogleFormSpam-0.0.1.dist-info/WHEEL
GoogleFormSpam-0.0.1.dist-info/top_level.txt
GoogleFormSpam-0.0.1.dist-info/RECORD
